[
  {
    "title": "Mojang partners with Merlin Entertainments for the world's first Minecraft theme park, Minecraft World",
    "url": "https://www.gamesindustry.biz/mojang-partners-with-merlin-entertainments-for-the-worlds-first-minecraft-theme-park-minecraft-world",
    "source": "GamesIndustry.biz",
    "pub_date": "2026-03-23",
    "category": "IP",
    "summary_ko": [
      "마인크래프트(Minecraft) 개발사 모장(Mojang)이 글로벌 테마파크 운영사 멀린 엔터테인먼트(Merlin Entertainments)와 파트너십을 체결했습니다.",
      "양사는 영국 내에 세계 최초의 마인크래프트 테마파크인 '마인크래프트 월드(Minecraft World)'를 구축하기로 결정했습니다.",
      "이번 협력을 통해 인기 IP인 마인크래프트를 오프라인 공간으로 확장하여 게임 이용자들에게 새로운 브랜드 경험을 제공할 예정입니다."
    ],
    "event": {
      "jurisdiction": "UK",
      "event_type": "business",
      "regulatory_phase": "enacted",
      "actors": [
        "Mojang",
        "Merlin Entertainments"
      ],
      "object": "Minecraft",
      "action": "licensing and physical expansion",
      "game_mechanic": null,
      "time_hint": "2024"
    },
    "event_key": "e40b34edd3bd4113",
    "is_primary": true,
    "title_ko": "모장(Mojang), 멀린 엔터테인먼트(Merlin Entertainments)와 협력해 세계 최초 마인크래프트 테마파크 '마인크래프트 월드' 조성"
  },
  {
    "title": "Savvy Games acquires Mobile Legends developer Moonton for $6 billion",
    "url": "https://www.gamesindustry.biz/savvy-games-acquires-mobile-legends-developer-moonton-for-6-billion",
    "source": "GamesIndustry.biz",
    "pub_date": "2026-03-23",
    "category": "MA_CORP_ANTITRUST",
    "summary_ko": [
      "사우디아라비아 국부펀드 산하의 새비 게임즈(Savvy Games)가 문톤(Moonton)을 60억 달러에 인수하기로 결정했습니다.",
      "이번 거래를 통해 틱톡(TikTok) 모회사인 바이트댄스(ByteDance)는 자회사였던 문톤(Moonton)을 매각하게 되었습니다.",
      "문톤(Moonton)은 글로벌 인기 모바일 게임인 '모바일 레전드: Bang Bang'의 개발사로 잘 알려져 있습니다."
    ],
    "event": {
      "jurisdiction": "Global",
      "event_type": "business",
      "regulatory_phase": "enacted",
      "actors": [
        "Savvy Games",
        "Moonton",
        "ByteDance"
      ],
      "object": "Moonton",
      "action": "acquisition",
      "game_mechanic": null,
      "time_hint": "2025-03-24"
    },
    "event_key": "0f6955be054f01ff",
    "is_primary": true,
    "title_ko": "새비 게임즈(Savvy Games), '모바일 레전드' 개발사 문톤(Moonton)을 60억 달러에 인수"
  },
  {
    "title": "Roblox insists plans to start charging creators for brand integrations \"is not about revenue at all\"",
    "url": "https://www.gamesindustry.biz/roblox-insists-plans-to-start-charging-creators-for-brand-integrations-is-not-about-revenue-at-all",
    "source": "GamesIndustry.biz",
    "pub_date": "2026-03-23",
    "category": "PLATFORM_PUBLISHING",
    "summary_ko": [
      "로블록스(Roblox)는 내년부터 자사 플랫폼 내 브랜드 통합 콘텐츠를 게시하는 제작자에게 수수료를 부과할 예정입니다.",
      "이번 정책은 플랫폼 내 브랜드 콘텐츠의 관리와 품질 향상을 위한 조치이며, 수익 창출이 주된 목적은 아니라고 밝혔습니다.",
      "업계에서는 플랫폼 내 생태계 관리 및 규제 강화 차원의 움직임으로 해석하고 있습니다."
    ],
    "event": {
      "jurisdiction": "Global",
      "event_type": "business",
      "regulatory_phase": "enacted",
      "actors": [
        "Roblox",
        "Creators"
      ],
      "object": "Brand integrations",
      "action": "Charging fees for platform content publication",
      "game_mechanic": "In-game monetization",
      "time_hint": "Next year"
    },
    "event_key": "28e3f1bddbbb0ede",
    "is_primary": true,
    "title_ko": "로블록스(Roblox), 브랜드 통합 콘텐츠 제작자에게 수수료 부과 계획은 수익 목적이 아니라고 강조"
  },
  {
    "title": "Pearl Abyss to conduct \"comprehensive audit\" after AI-generated art found in Crimson Desert",
    "url": "https://www.gamesindustry.biz/pearl-abyss-to-conduct-comprehensive-audit-after-ai-generated-art-found-in-crimson-desert",
    "source": "GamesIndustry.biz",
    "pub_date": "2026-03-23",
    "category": "AI_EMERGING",
    "summary_ko": [
      "펄어비스(Pearl Abyss)는 개발 중인 게임 '붉은사막(Crimson Desert)'의 게임 내 에셋에서 AI가 생성한 이미지가 의도치 않게 포함된 사실을 확인했습니다.",
      "해당 이슈와 관련하여 펄어비스(Pearl Abyss)는 문제의 원인을 파악하고 재발을 방지하기 위해 전체 게임 에셋에 대한 전면적인 감사를 진행할 예정입니다.",
      "최근 게임 업계에서 생성형 AI 활용에 대한 논란이 커짐에 따라, 이번 조치는 개발 리소스 관리와 저작권 보호에 대한 책임 경영의 일환으로 풀이됩니다."
    ],
    "event": {
      "jurisdiction": "Global",
      "event_type": "other",
      "regulatory_phase": "enforced",
      "actors": [
        "Pearl Abyss"
      ],
      "object": "in-game assets",
      "action": "comprehensive audit",
      "game_mechanic": "in-game assets",
      "time_hint": "post-discovery"
    },
    "event_key": "25c2ae432895db27",
    "is_primary": true,
    "title_ko": "펄어비스(Pearl Abyss), '붉은사막(Crimson Desert)' 내 AI 생성 이미지 발견에 따른 전면 감사 실시"
  },
  {
    "title": "Nintendo reportedly planning revised Switch 2 model with replaceable battery in EU",
    "url": "https://www.gamesindustry.biz/nintendo-reportedly-planning-revised-switch-2-model-with-replaceable-battery-in-eu",
    "source": "GamesIndustry.biz",
    "pub_date": "2026-03-23",
    "category": "CONSUMER_MONETIZATION",
    "summary_ko": [
      "닌텐도(Nintendo)가 유럽연합(EU)의 배터리 규제에 대응하기 위해 교체형 배터리를 탑재한 차세대 기기 스위치(Switch) 2의 개량형 모델을 준비 중인 것으로 알려졌습니다.",
      "이번 조치는 최근 강화된 EU의 소비자 전자제품 배터리 교체 용이성 관련 법안을 준수하여 현지 시장에서의 판매 전략을 최적화하기 위한 것으로 분석됩니다.",
      "해당 설계 변경이 글로벌 표준 모델 전체에 적용될지 혹은 EU 전용 모델로 한정될지 여부가 향후 게임 하드웨어 시장의 규제 대응 사례로 주목받고 있습니다."
    ],
    "event": {
      "jurisdiction": "EU",
      "event_type": "policy",
      "regulatory_phase": "enacted",
      "actors": [
        "Nintendo"
      ],
      "object": "Switch 2",
      "action": "hardware modification for battery accessibility",
      "game_mechanic": null,
      "time_hint": "future"
    },
    "event_key": "1d82c914c7bd62f0",
    "is_primary": true,
    "title_ko": "닌텐도(Nintendo), EU 시장용 교체형 배터리 탑재 스위치(Switch) 2 모델 개발 보도"
  },
  {
    "title": "The DLSS 5 backlash is not going away | Opinion",
    "url": "https://www.gamesindustry.biz/the-dlss-5-backlash-is-not-going-away-opinion",
    "source": "GamesIndustry.biz",
    "pub_date": "2026-03-20",
    "category": "AI_EMERGING",
    "summary_ko": [
      "엔비디아(Nvidia)가 최근 공개한 DLSS 5 기술에 대해 게임 업계와 이용자들의 거센 반발이 이어지고 있습니다.",
      "이번 논란은 단순한 일시적 불만이 아니라, 기술적 방향성과 시장 영향력에 대한 근본적인 의구심이 반영된 결과로 분석됩니다.",
      "업계 관계자들은 이러한 거부 반응이 장기화될 조짐을 보임에 따라, 엔비디아(Nvidia)의 대응 전략에 대한 비판적 시각을 견지하고 있습니다."
    ],
    "event": {
      "jurisdiction": "Global",
      "event_type": "other",
      "regulatory_phase": "proposed",
      "actors": [
        "Nvidia",
        "Consumers"
      ],
      "object": "DLSS 5 technology",
      "action": "public discourse and industry backlash regarding AI-based upscaling technology",
      "game_mechanic": "upscaling",
      "time_hint": "this week"
    },
    "event_key": "43fe2cc331416cee",
    "is_primary": true,
    "title_ko": "가라앉지 않는 엔비디아(Nvidia)의 DLSS 5 기술 반발 | 칼럼"
  },
  {
    "title": "This mobile game has been made using AI for a year now – and no one noticed",
    "url": "https://www.gamesindustry.biz/this-mobile-game-has-been-made-using-ai-for-a-year-now-and-no-one-noticed",
    "source": "GamesIndustry.biz",
    "pub_date": "2026-03-20",
    "category": "AI_EMERGING",
    "summary_ko": [
      "게임스인더스트리(GamesIndustry.biz)의 AI 주간 기획에 따르면, 특정 모바일 게임이 지난 1년간 생성형 AI를 활용해 개발되었으나 이용자들은 이를 인지하지 못했습니다.",
      "개발사는 AI 도구를 활용해 제작 공정의 효율성을 높였으며, 결과물의 품질이 기존 방식과 차이가 없었음을 입증했습니다.",
      "이번 사례는 게임 개발 분야에서 AI 기술의 실질적인 활용 가능성과 그에 따른 품질 관리의 중요성을 시사합니다."
    ],
    "event": {
      "jurisdiction": "Global",
      "event_type": "other",
      "regulatory_phase": "proposed",
      "actors": [
        "Game developers",
        "GamesIndustry.biz"
      ],
      "object": "Generative AI in game development",
      "action": "Integration of AI tools in mobile game production",
      "game_mechanic": "Content generation",
      "time_hint": "One year"
    },
    "event_key": "a1b2455a4adc4bee",
    "is_primary": true,
    "title_ko": "이 모바일 게임은 1년간 AI로 제작되었지만 아무도 눈치채지 못했다"
  },
  {
    "title": "Unknown Worlds co-founders' lawyers accuse Krafton of  \"intentionally leaking\" Subnautica 2 release date",
    "url": "https://www.gamesindustry.biz/unknown-worlds-co-founders-lawyers-accuse-krafton-of-intentionally-leaking-subnautica-2-release-date",
    "source": "GamesIndustry.biz",
    "pub_date": "2026-03-20",
    "category": "MA_CORP_ANTITRUST",
    "summary_ko": [
      "언노운 월즈(Unknown Worlds)의 공동 창립자인 테드 길(Ted Gill), 찰리 클리블랜드(Charlie Cleveland), 맥스 맥과이어(Max McGuire) 측 변호인단이 크래프톤(Krafton)을 고소했습니다.",
      "변호인단은 크래프톤(Krafton)이 내부 문건을 통해 '서브노티카 2(Subnautica 2)'의 5월 얼리 액세스 출시 계획을 고의로 유출했다고 주장했습니다.",
      "양측 간의 갈등이 심화되는 가운데, 이번 정보 유출 건이 향후 기업 경영 및 지식재산권 분쟁에 미칠 영향에 업계의 관심이 쏠리고 있습니다."
    ],
    "event": {
      "jurisdiction": "Global",
      "event_type": "litigation",
      "regulatory_phase": "litigation",
      "actors": [
        "Unknown Worlds co-founders",
        "Krafton"
      ],
      "object": "Subnautica 2 release date memo",
      "action": "accusal of intentional leaking",
      "game_mechanic": "early access",
      "time_hint": "May"
    },
    "event_key": "932f4e5bc7187ddc",
    "is_primary": true,
    "title_ko": "언노운 월즈(Unknown Worlds) 공동 창립자 측, 크래프톤(Krafton)의 서브노티카 2(Subnautica 2) 출시일 고의 유출 주장"
  },
  {
    "title": "ESRB will not adopt PEGI age-rating changes in the US as it \"could be confusing\"",
    "url": "https://www.gamesindustry.biz/esrb-will-not-adopt-pegi-age-rating-changes-in-the-us-as-it-could-be-confusing",
    "source": "GamesIndustry.biz",
    "pub_date": "2026-03-20",
    "category": "CONTENT_AGE",
    "summary_ko": [
      "미국 게임 등급 심의 기구인 ESRB(Entertainment Software Rating Board)는 유럽의 PEGI(Pan-European Games Information)가 발표한 연령 등급 체계 변경을 미국에 적용하지 않기로 결정했습니다.",
      "ESRB는 해당 변경 사항을 도입할 경우 오히려 미국 내 이용자들에게 혼란을 줄 수 있다는 점을 거부 이유로 밝혔습니다.",
      "이번 결정으로 미국과 유럽 시장의 게임 연령 등급 심사 기준은 향후 서로 다른 체계를 유지할 전망입니다."
    ],
    "event": {
      "jurisdiction": "US",
      "event_type": "policy",
      "regulatory_phase": "enforced",
      "actors": [
        "ESRB",
        "PEGI"
      ],
      "object": "age-rating system",
      "action": "rejection of policy harmonization",
      "game_mechanic": "loot boxes",
      "time_hint": "current"
    },
    "event_key": "dbefdf1713aefb48",
    "is_primary": true,
    "title_ko": "ESRB, 미국 내 PEGI 연령 등급 변경 사항 도입 거부… \"혼란 초래 가능\""
  },
  {
    "title": "Sony closes first-party studio Dark Outlaw Games",
    "url": "https://www.gamesindustry.biz/sony-closes-first-party-studio-dark-outlaw-games",
    "source": "GamesIndustry.biz",
    "pub_date": "2026-03-25",
    "category": "MA_CORP_ANTITRUST",
    "summary_ko": [
      "소니(Sony)가 자사 퍼스트 파티 스튜디오인 다크 아웃로 게임즈(Dark Outlaw Games)의 운영을 종료함.",
      "이번 폐쇄 결정으로 해당 스튜디오가 진행하던 프로젝트와 인력 운용에 변화가 생길 전망임.",
      "최근 게임 업계의 구조조정 흐름 속에서 소니(Sony)의 개발 조직 효율화 전략의 일환으로 풀이됨."
    ],
    "event": {
      "jurisdiction": "Global",
      "event_type": "business",
      "regulatory_phase": "enacted",
      "actors": [
        "Sony",
        "Dark Outlaw Games"
      ],
      "object": "First-party game studio",
      "action": "studio closure",
      "game_mechanic": null,
      "time_hint": "present"
    },
    "event_key": "197458d9d20a7d13",
    "is_primary": true,
    "title_ko": "소니(Sony), 퍼스트 파티 스튜디오 다크 아웃로 게임즈(Dark Outlaw Games) 폐쇄"
  }
]